configomatic/__init__.py
configomatic/configuration.py
configomatic/exceptions.py
configomatic/loader.py
configomatic/logging.py
configomatic/utils.py
configomatic-0.4.0.dist-info/METADATA
configomatic-0.4.0.dist-info/WHEEL
configomatic-0.4.0.dist-info/top_level.txt
configomatic-0.4.0.dist-info/RECORD
