Metadata-Version: 2.1
Name: configomatic
Version: 0.4.0
Summary: Package providing a configurable object for use in Python applications.
Home-page: https://github.com/azimuth-cloud/configomatic
Author: Matt Pryor
Author-email: matt@stackhpc.com
Requires-Dist: pydantic
Provides-Extra: all
Requires-Dist: pyyaml ; extra == 'all'
Requires-Dist: toml ; extra == 'all'
Provides-Extra: toml
Requires-Dist: toml ; extra == 'toml'
Provides-Extra: yaml
Requires-Dist: pyyaml ; extra == 'yaml'
